ep/__init__.py
ep/compare.py
ep/evaluate.py
ep/evaluate_frame.py
ep/evalplatform/__init__.py
ep/evalplatform/create_report.py
ep/evalplatform/debug.py
ep/evalplatform/draw_details.py
ep/evalplatform/gather_results.py
ep/evalplatform/parsers.py
ep/evalplatform/parsers_image.py
ep/evalplatform/plot_comparison.py
ep/evalplatform/utils.py
ep/evalplatform/yeast_datatypes.py
evalplatform-1.2.0.dist-info/LICENSE
evalplatform-1.2.0.dist-info/METADATA
evalplatform-1.2.0.dist-info/WHEEL
evalplatform-1.2.0.dist-info/top_level.txt
evalplatform-1.2.0.dist-info/RECORD
