Metadata-Version: 2.1
Name: evalplatform
Version: 1.2.0
Summary: Evaluation Platform
Home-page: https://github.com/Fafa87/EP
Author: Filip Mroz
Author-email: fafafft@gmail.com
License: BSD
Keywords: evaluation,precision,recall
Platform: UNKNOWN
Classifier: Development Status :: 5 - Production/Stable
Classifier: Intended Audience :: Science/Research
Classifier: License :: OSI Approved :: BSD License
Classifier: Operating System :: OS Independent
Classifier: Programming Language :: Python :: 2.7
Classifier: Programming Language :: Python :: 3.5
Classifier: Programming Language :: Python :: 3.7
Classifier: Topic :: Scientific/Engineering
